MANIFEST.in
setup.py
pygeomod/__init__.py
pygeomod/geogrid.py
pygeomod/geomodeller_xml_obj.py
pygeomod/struct_data.py
pygeomod.egg-info/PKG-INFO
pygeomod.egg-info/SOURCES.txt
pygeomod.egg-info/dependency_links.txt
pygeomod.egg-info/top_level.txt