Metadata-Version: 1.1
Name: pygeomod
Version: 0.2.0
Summary: Python wrappers for Geomodeller API and input files
Home-page: http://github.com/flohorovicic/pygeomod
Author: Florian Wellmann
Author-email: flohorovicic@gmail.com
License: MIT
Platform: UNKNOWN
Classifier: Development Status :: 2 - Pre-Alpha
Classifier: Intended Audience :: Science/Research
Classifier: Programming Language :: Python :: 2.7
Classifier: Intended Audience :: Education
Classifier: Topic :: Education
Classifier: Topic :: Scientific/Engineering
Classifier: Topic :: Scientific/Engineering :: Physics
Classifier: Topic :: Scientific/Engineering :: Visualization
Classifier: License :: OSI Approved :: MIT License
